hyper_surrogate/__init__.py
hyper_surrogate/deformation_gradient.py
hyper_surrogate/generator.py
hyper_surrogate/kinematics.py
hyper_surrogate/materials.py
hyper_surrogate/reporter.py
hyper_surrogate/symbolic.py
hyper_surrogate/umat_handler.py
hyper_surrogate-0.0.2.dist-info/LICENSE
hyper_surrogate-0.0.2.dist-info/METADATA
hyper_surrogate-0.0.2.dist-info/WHEEL
hyper_surrogate-0.0.2.dist-info/RECORD
