Metadata-Version: 2.1
Name: hyper_surrogate
Version: 0.0.2
Summary: Hyperelastic Surrogates
Home-page: https://github.com/jpsferreira/hyper-surrogate
Author: Joao Ferreira
Author-email: fj.ferreira@fe.up.pt
Requires-Python: >=3.10,<4.0
Classifier: Programming Language :: Python :: 3
Classifier: Programming Language :: Python :: 3.10
Classifier: Programming Language :: Python :: 3.11
Classifier: Programming Language :: Python :: 3.12
Classifier: Programming Language :: Python :: 3.13
Requires-Dist: matplotlib (>=3.8.3,<4.0.0)
Requires-Dist: numpy (>=1.26.4,<2.0.0)
Requires-Dist: pandas (>=2.2.3,<3.0.0)
Requires-Dist: seaborn (>=0.13.2,<0.14.0)
Requires-Dist: sympy (>=1.12,<2.0)
Requires-Dist: tqdm (>=4.66.5,<5.0.0)
Project-URL: Documentation, https://jpsferreira.github.io/hyper-surrogate/
Project-URL: Repository, https://github.com/jpsferreira/hyper-surrogate
